nioflux_mq/__init__.py
nioflux_mq/client/__init__.py
nioflux_mq/client/client.py
nioflux_mq/client/response.py
nioflux_mq/handler/__init__.py
nioflux_mq/handler/json_dump_handler.py
nioflux_mq/handler/json_load_handler.py
nioflux_mq/handler/mq_protocol_handler.py
nioflux_mq/handler/response_handler.py
nioflux_mq/mq/__init__.py
nioflux_mq/mq/message.py
nioflux_mq/mq/message_queue.py
nioflux_mq/server/__init__.py
nioflux_mq/server/__main__.py
nioflux_mq/server/server.py
nioflux_mq/snapshot/__init__.py
nioflux_mq-0.0.1.dist-info/licenses/LICENSE
nioflux_mq-0.0.1.dist-info/METADATA
nioflux_mq-0.0.1.dist-info/WHEEL
nioflux_mq-0.0.1.dist-info/top_level.txt
nioflux_mq-0.0.1.dist-info/RECORD
