Metadata-Version: 2.4
Name: nioflux-mq
Version: 0.0.1
Summary: A thread-safe message queue implementation.
Requires-Python: >=3.10
License-File: LICENSE
Requires-Dist: nioflux>=0.0.2
Dynamic: license-file
